medux/plugins/timetracker/__init__.py
medux/plugins/timetracker/admin.py
medux/plugins/timetracker/apps.py
medux/plugins/timetracker/bootstrap.py
medux/plugins/timetracker/calendars.py
medux/plugins/timetracker/components.py
medux/plugins/timetracker/conf.py
medux/plugins/timetracker/forms.py
medux/plugins/timetracker/menus.py
medux/plugins/timetracker/models.py
medux/plugins/timetracker/signals.py
medux/plugins/timetracker/urls.py
medux/plugins/timetracker/views.py
medux_timetracker-0.0.1.dist-info/LICENSE.md
medux_timetracker-0.0.1.dist-info/METADATA
medux_timetracker-0.0.1.dist-info/WHEEL
medux_timetracker-0.0.1.dist-info/entry_points.txt
medux_timetracker-0.0.1.dist-info/top_level.txt
medux_timetracker-0.0.1.dist-info/RECORD
