Metadata-Version: 2.1
Name: medux-timetracker
Version: 0.0.1
Summary: MedUX timetracking plugin for employees
Author-email: Christian González <office@nerdocs.at>
License: ### GNU AFFERO GENERAL PUBLIC LICENSE
Project-URL: Home, https://medux-timetracker.readthedocs.org
Classifier: Development Status :: 2 - Pre-Alpha
Classifier: Environment :: Web Environment
Classifier: Framework :: Django :: 4.1
Classifier: Intended Audience :: Developers
Classifier: License :: OSI Approved :: GNU Affero General Public License v3 or later (AGPLv3+)
Classifier: Natural Language :: English
Classifier: Operating System :: OS Independent
Classifier: Topic :: Internet :: WWW/HTTP
Classifier: Topic :: Internet :: WWW/HTTP :: Dynamic Content
Requires-Python: >=3.10
License-File: LICENSE.md
Requires-Dist: medux (>=0.0.6)
Requires-Dist: holidays
